[
  {
    "name": "b3c.16x64",
    "provider": "classic",
    "memory": "64GB",
    "networkSpeed": "1000Mbps",
    "cores": "16",
    "os": "UBUNTU_18_64",
    "serverType": "virtual",
    "storage": "25GB",
    "secondaryStorage": "true",
    "secondaryStorageEncrypted": false,
    "deprecated": false,
    "correspondingMachineType": "",
    "isTrusted": false,
    "gpus": "",
    "ocp_unsupported": false
  },
  {
    "name": "b3c.16x64.300gb",
    "provider": "classic",
    "memory": "64GB",
    "networkSpeed": "1000Mbps",
    "cores": "16",
    "os": "UBUNTU_18_64",
    "serverType": "virtual",
    "storage": "25GB",
    "secondaryStorage": "true",
    "secondaryStorageEncrypted": false,
    "deprecated": false,
    "correspondingMachineType": "",
    "isTrusted": false,
    "gpus": "",
    "ocp_unsupported": false
  },
  {
    "name": "b3c.32x128",
    "provider": "classic",
    "memory": "128GB",
    "networkSpeed": "1000Mbps",
    "cores": "32",
    "os": "UBUNTU_18_64",
    "serverType": "virtual",
    "storage": "25GB",
    "secondaryStorage": "true",
    "secondaryStorageEncrypted": false,
    "deprecated": false,
    "correspondingMachineType": "",
    "isTrusted": false,
    "gpus": "",
    "ocp_unsupported": false
  },
  {
    "name": "b3c.4x16",
    "provider": "classic",
    "memory": "16GB",
    "networkSpeed": "1000Mbps",
    "cores": "4",
    "os": "UBUNTU_18_64",
    "serverType": "virtual",
    "storage": "25GB",
    "secondaryStorage": "true",
    "secondaryStorageEncrypted": false,
    "deprecated": false,
    "correspondingMachineType": "",
    "isTrusted": false,
    "gpus": "",
    "ocp_unsupported": false
  },
  {
    "name": "b3c.56x242",
    "provider": "classic",
    "memory": "242GB",
    "networkSpeed": "1000Mbps",
    "cores": "56",
    "os": "UBUNTU_18_64",
    "serverType": "virtual",
    "storage": "25GB",
    "secondaryStorage": "true",
    "secondaryStorageEncrypted": false,
    "deprecated": false,
    "correspondingMachineType": "",
    "isTrusted": false,
    "gpus": "",
    "ocp_unsupported": false
  },
  {
    "name": "b3c.8x32",
    "provider": "classic",
    "memory": "32GB",
    "networkSpeed": "1000Mbps",
    "cores": "8",
    "os": "UBUNTU_18_64",
    "serverType": "virtual",
    "storage": "25GB",
    "secondaryStorage": "true",
    "secondaryStorageEncrypted": false,
    "deprecated": false,
    "correspondingMachineType": "",
    "isTrusted": false,
    "gpus": "",
    "ocp_unsupported": false
  },
  {
    "name": "c3c.16x16",
    "provider": "classic",
    "memory": "16GB",
    "networkSpeed": "1000Mbps",
    "cores": "16",
    "os": "UBUNTU_18_64",
    "serverType": "virtual",
    "storage": "25GB",
    "secondaryStorage": "true",
    "secondaryStorageEncrypted": false,
    "deprecated": false,
    "correspondingMachineType": "",
    "isTrusted": false,
    "gpus": "",
    "ocp_unsupported": false
  },
  {
    "name": "c3c.16x32",
    "provider": "classic",
    "memory": "32GB",
    "networkSpeed": "1000Mbps",
    "cores": "16",
    "os": "UBUNTU_18_64",
    "serverType": "virtual",
    "storage": "25GB",
    "secondaryStorage": "true",
    "secondaryStorageEncrypted": false,
    "deprecated": false,
    "correspondingMachineType": "",
    "isTrusted": false,
    "gpus": "",
    "ocp_unsupported": false
  },
  {
    "name": "c3c.32x32",
    "provider": "classic",
    "memory": "32GB",
    "networkSpeed": "1000Mbps",
    "cores": "32",
    "os": "UBUNTU_18_64",
    "serverType": "virtual",
    "storage": "25GB",
    "secondaryStorage": "true",
    "secondaryStorageEncrypted": false,
    "deprecated": false,
    "correspondingMachineType": "",
    "isTrusted": false,
    "gpus": "",
    "ocp_unsupported": false
  },
  {
    "name": "c3c.32x64",
    "provider": "classic",
    "memory": "64GB",
    "networkSpeed": "1000Mbps",
    "cores": "32",
    "os": "UBUNTU_18_64",
    "serverType": "virtual",
    "storage": "25GB",
    "secondaryStorage": "true",
    "secondaryStorageEncrypted": false,
    "deprecated": false,
    "correspondingMachineType": "",
    "isTrusted": false,
    "gpus": "",
    "ocp_unsupported": false
  },
  {
    "name": "m3c.4x32",
    "provider": "classic",
    "memory": "32GB",
    "networkSpeed": "1000Mbps",
    "cores": "4",
    "os": "UBUNTU_18_64",
    "serverType": "virtual",
    "storage": "25GB",
    "secondaryStorage": "true",
    "secondaryStorageEncrypted": false,
    "deprecated": false,
    "correspondingMachineType": "",
    "isTrusted": false,
    "gpus": "",
    "ocp_unsupported": false
  },
  {
    "name": "mb4c.20x192",
    "provider": "classic",
    "memory": "192GB",
    "networkSpeed": "10000Mbps",
    "cores": "20",
    "os": "UBUNTU_18_64",
    "serverType": "physical",
    "storage": "2000GB",
    "secondaryStorage": "true",
    "secondaryStorageEncrypted": false,
    "deprecated": false,
    "correspondingMachineType": "",
    "isTrusted": false,
    "gpus": "",
    "ocp_unsupported": false
  },
  {
    "name": "mb4c.20x384",
    "provider": "classic",
    "memory": "384GB",
    "networkSpeed": "10000Mbps",
    "cores": "20",
    "os": "UBUNTU_18_64",
    "serverType": "physical",
    "storage": "2000GB",
    "secondaryStorage": "true",
    "secondaryStorageEncrypted": false,
    "deprecated": false,
    "correspondingMachineType": "",
    "isTrusted": false,
    "gpus": "",
    "ocp_unsupported": false
  },
  {
    "name": "mb4c.20x64",
    "provider": "classic",
    "memory": "64GB",
    "networkSpeed": "10000Mbps",
    "cores": "20",
    "os": "UBUNTU_18_64",
    "serverType": "physical",
    "storage": "2000GB",
    "secondaryStorage": "true",
    "secondaryStorageEncrypted": false,
    "deprecated": false,
    "correspondingMachineType": "",
    "isTrusted": false,
    "gpus": "",
    "ocp_unsupported": false
  },
  {
    "name": "mb4c.20x64.2x1.9tb.ssd",
    "provider": "classic",
    "memory": "64GB",
    "networkSpeed": "10000Mbps",
    "cores": "20",
    "os": "UBUNTU_18_64",
    "serverType": "physical",
    "storage": "2000GB",
    "secondaryStorage": "true",
    "secondaryStorageEncrypted": false,
    "deprecated": false,
    "correspondingMachineType": "",
    "isTrusted": false,
    "gpus": "",
    "ocp_unsupported": false
  },
  {
    "name": "mb4c.32x384.3.8tb.ssd",
    "provider": "classic",
    "memory": "384GB",
    "networkSpeed": "10000Mbps",
    "cores": "32",
    "os": "UBUNTU_18_64",
    "serverType": "physical",
    "storage": "2000GB",
    "secondaryStorage": "true",
    "secondaryStorageEncrypted": false,
    "deprecated": false,
    "correspondingMachineType": "",
    "isTrusted": false,
    "gpus": "",
    "ocp_unsupported": false
  },
  {
    "name": "mb4c.32x384.6x3.8tb.ssd",
    "provider": "classic",
    "memory": "384GB",
    "networkSpeed": "10000Mbps",
    "cores": "32",
    "os": "UBUNTU_18_64",
    "serverType": "physical",
    "storage": "2000GB",
    "secondaryStorage": "true",
    "secondaryStorageEncrypted": false,
    "deprecated": false,
    "correspondingMachineType": "",
    "isTrusted": false,
    "gpus": "",
    "ocp_unsupported": false
  },
  {
    "name": "mb4c.32x768.3.8tb.ssd",
    "provider": "classic",
    "memory": "768GB",
    "networkSpeed": "10000Mbps",
    "cores": "32",
    "os": "UBUNTU_18_64",
    "serverType": "physical",
    "storage": "2000GB",
    "secondaryStorage": "true",
    "secondaryStorageEncrypted": false,
    "deprecated": false,
    "correspondingMachineType": "",
    "isTrusted": false,
    "gpus": "",
    "ocp_unsupported": false
  },
  {
    "name": "mb4c.48x1536",
    "provider": "classic",
    "memory": "1536GB",
    "networkSpeed": "10000Mbps",
    "cores": "48",
    "os": "UBUNTU_18_64",
    "serverType": "physical",
    "storage": "2000GB",
    "secondaryStorage": "true",
    "secondaryStorageEncrypted": false,
    "deprecated": false,
    "correspondingMachineType": "",
    "isTrusted": false,
    "gpus": "",
    "ocp_unsupported": false
  },
  {
    "name": "me4c.4x32",
    "provider": "classic",
    "memory": "32GB",
    "networkSpeed": "10000Mbps",
    "cores": "4",
    "os": "UBUNTU_18_64",
    "serverType": "physical",
    "storage": "2000GB",
    "secondaryStorage": "true",
    "secondaryStorageEncrypted": false,
    "deprecated": false,
    "correspondingMachineType": "",
    "isTrusted": false,
    "gpus": "",
    "ocp_unsupported": false
  },
  {
    "name": "me4c.4x32.1.9tb.ssd",
    "provider": "classic",
    "memory": "32GB",
    "networkSpeed": "10000Mbps",
    "cores": "4",
    "os": "UBUNTU_18_64",
    "serverType": "physical",
    "storage": "2000GB",
    "secondaryStorage": "true",
    "secondaryStorageEncrypted": false,
    "deprecated": false,
    "correspondingMachineType": "",
    "isTrusted": false,
    "gpus": "",
    "ocp_unsupported": false
  },
  {
    "name": "mg4c.32x384.2xp100",
    "provider": "classic",
    "memory": "384GB",
    "networkSpeed": "10000Mbps",
    "cores": "32",
    "os": "UBUNTU_18_64",
    "serverType": "physical",
    "storage": "2000GB",
    "secondaryStorage": "true",
    "secondaryStorageEncrypted": false,
    "deprecated": false,
    "correspondingMachineType": "",
    "isTrusted": false,
    "gpus": "2x_P100",
    "ocp_unsupported": false
  },
  {
    "name": "mg4c.48x384.2xv100",
    "provider": "classic",
    "memory": "384GB",
    "networkSpeed": "10000Mbps",
    "cores": "48",
    "os": "UBUNTU_18_64",
    "serverType": "physical",
    "storage": "2000GB",
    "secondaryStorage": "true",
    "secondaryStorageEncrypted": false,
    "deprecated": false,
    "correspondingMachineType": "",
    "isTrusted": false,
    "gpus": "2x_V100",
    "ocp_unsupported": false
  },
  {
    "name": "u3c.2x4",
    "provider": "classic",
    "memory": "4GB",
    "networkSpeed": "1000Mbps",
    "cores": "2",
    "os": "UBUNTU_18_64",
    "serverType": "virtual",
    "storage": "25GB",
    "secondaryStorage": "true",
    "secondaryStorageEncrypted": false,
    "deprecated": false,
    "correspondingMachineType": "",
    "isTrusted": false,
    "gpus": "",
    "ocp_unsupported": false
  }
]
