[
  {
    "name": "bx2.16x64",
    "provider": "vpc-gen2",
    "cpu": 16,
    "memory": 64,
    "networkSpeed": "24Gbps",
    "serverType": "virtual",
    "secondaryStorage": "false",
    "secondaryStorageEncrypted": false,
    "deprecated": false,
    "correspondingMachineType": "",
    "isTrusted": false,
    "gpus": "",
    "ocp_unsupported": false
  },
  {
    "name": "bx2.2x8",
    "provider": "vpc-gen2",
    "cpu": 2,
    "memory": 8,
    "networkSpeed": "4Gbps",
    "serverType": "virtual",
    "secondaryStorage": "false",
    "secondaryStorageEncrypted": false,
    "deprecated": false,
    "correspondingMachineType": "",
    "isTrusted": false,
    "gpus": "",
    "ocp_unsupported": false
  },
  {
    "name": "bx2.32x128",
    "provider": "vpc-gen2",
    "cpu": 32,
    "memory": 128,
    "networkSpeed": "25Gbps",
    "serverType": "virtual",
    "secondaryStorage": "false",
    "secondaryStorageEncrypted": false,
    "deprecated": false,
    "correspondingMachineType": "",
    "isTrusted": false,
    "gpus": "",
    "ocp_unsupported": false
  },
  {
    "name": "bx2.48x192",
    "provider": "vpc-gen2",
    "cpu": 48,
    "memory": 192,
    "networkSpeed": "25Gbps",
    "serverType": "virtual",
    "secondaryStorage": "false",
    "secondaryStorageEncrypted": false,
    "deprecated": false,
    "correspondingMachineType": "",
    "isTrusted": false,
    "gpus": "",
    "ocp_unsupported": false
  },
  {
    "name": "bx2.4x16",
    "provider": "vpc-gen2",
    "cpu": 4,
    "memory": 16,
    "networkSpeed": "8Gbps",
    "serverType": "virtual",
    "secondaryStorage": "false",
    "secondaryStorageEncrypted": false,
    "deprecated": false,
    "correspondingMachineType": "",
    "isTrusted": false,
    "gpus": "",
    "ocp_unsupported": false
  },
  {
    "name": "bx2.8x32",
    "provider": "vpc-gen2",
    "cpu": 8,
    "memory": 32,
    "networkSpeed": "16Gbps",
    "serverType": "virtual",
    "secondaryStorage": "false",
    "secondaryStorageEncrypted": false,
    "deprecated": false,
    "correspondingMachineType": "",
    "isTrusted": false,
    "gpus": "",
    "ocp_unsupported": false
  },
  {
    "name": "cx2.16x32",
    "provider": "vpc-gen2",
    "cpu": 16,
    "memory": 32,
    "networkSpeed": "24Gbps",
    "serverType": "virtual",
    "secondaryStorage": "false",
    "secondaryStorageEncrypted": false,
    "deprecated": false,
    "correspondingMachineType": "",
    "isTrusted": false,
    "gpus": "",
    "ocp_unsupported": false
  },
  {
    "name": "cx2.2x4",
    "provider": "vpc-gen2",
    "cpu": 2,
    "memory": 4,
    "networkSpeed": "4Gbps",
    "serverType": "virtual",
    "secondaryStorage": "false",
    "secondaryStorageEncrypted": false,
    "deprecated": false,
    "correspondingMachineType": "",
    "isTrusted": false,
    "gpus": "",
    "ocp_unsupported": false
  },
  {
    "name": "cx2.32x64",
    "provider": "vpc-gen2",
    "cpu": 32,
    "memory": 64,
    "networkSpeed": "25Gbps",
    "serverType": "virtual",
    "secondaryStorage": "false",
    "secondaryStorageEncrypted": false,
    "deprecated": false,
    "correspondingMachineType": "",
    "isTrusted": false,
    "gpus": "",
    "ocp_unsupported": false
  },
  {
    "name": "cx2.48x96",
    "provider": "vpc-gen2",
    "cpu": 48,
    "memory": 96,
    "networkSpeed": "25Gbps",
    "serverType": "virtual",
    "secondaryStorage": "false",
    "secondaryStorageEncrypted": false,
    "deprecated": false,
    "correspondingMachineType": "",
    "isTrusted": false,
    "gpus": "",
    "ocp_unsupported": false
  },
  {
    "name": "cx2.4x8",
    "provider": "vpc-gen2",
    "cpu": 4,
    "memory": 8,
    "networkSpeed": "8Gbps",
    "serverType": "virtual",
    "secondaryStorage": "false",
    "secondaryStorageEncrypted": false,
    "deprecated": false,
    "correspondingMachineType": "",
    "isTrusted": false,
    "gpus": "",
    "ocp_unsupported": false
  },
  {
    "name": "cx2.8x16",
    "provider": "vpc-gen2",
    "cpu": 8,
    "memory": 16,
    "networkSpeed": "16Gbps",
    "serverType": "virtual",
    "secondaryStorage": "false",
    "secondaryStorageEncrypted": false,
    "deprecated": false,
    "correspondingMachineType": "",
    "isTrusted": false,
    "gpus": "",
    "ocp_unsupported": false
  },
  {
    "name": "mx2.128x1024",
    "provider": "vpc-gen2",
    "cpu": 128,
    "memory": 1024,
    "networkSpeed": "25Gbps",
    "serverType": "virtual",
    "secondaryStorage": "false",
    "secondaryStorageEncrypted": false,
    "deprecated": false,
    "correspondingMachineType": "",
    "isTrusted": false,
    "gpus": "",
    "ocp_unsupported": false
  },
  {
    "name": "mx2.16x128",
    "provider": "vpc-gen2",
    "cpu": 16,
    "memory": 128,
    "networkSpeed": "24Gbps",
    "serverType": "virtual",
    "secondaryStorage": "false",
    "secondaryStorageEncrypted": false,
    "deprecated": false,
    "correspondingMachineType": "",
    "isTrusted": false,
    "gpus": "",
    "ocp_unsupported": false
  },
  {
    "name": "mx2.2x16",
    "provider": "vpc-gen2",
    "cpu": 2,
    "memory": 16,
    "networkSpeed": "4Gbps",
    "serverType": "virtual",
    "secondaryStorage": "false",
    "secondaryStorageEncrypted": false,
    "deprecated": false,
    "correspondingMachineType": "",
    "isTrusted": false,
    "gpus": "",
    "ocp_unsupported": false
  },
  {
    "name": "mx2.32x256",
    "provider": "vpc-gen2",
    "cpu": 32,
    "memory": 256,
    "networkSpeed": "25Gbps",
    "serverType": "virtual",
    "secondaryStorage": "false",
    "secondaryStorageEncrypted": false,
    "deprecated": false,
    "correspondingMachineType": "",
    "isTrusted": false,
    "gpus": "",
    "ocp_unsupported": false
  },
  {
    "name": "mx2.48x384",
    "provider": "vpc-gen2",
    "cpu": 48,
    "memory": 384,
    "networkSpeed": "25Gbps",
    "serverType": "virtual",
    "secondaryStorage": "false",
    "secondaryStorageEncrypted": false,
    "deprecated": false,
    "correspondingMachineType": "",
    "isTrusted": false,
    "gpus": "",
    "ocp_unsupported": false
  },
  {
    "name": "mx2.4x32",
    "provider": "vpc-gen2",
    "cpu": 4,
    "memory": 32,
    "networkSpeed": "8Gbps",
    "serverType": "virtual",
    "secondaryStorage": "false",
    "secondaryStorageEncrypted": false,
    "deprecated": false,
    "correspondingMachineType": "",
    "isTrusted": false,
    "gpus": "",
    "ocp_unsupported": false
  },
  {
    "name": "mx2.64x512",
    "provider": "vpc-gen2",
    "cpu": 64,
    "memory": 512,
    "networkSpeed": "25Gbps",
    "serverType": "virtual",
    "secondaryStorage": "false",
    "secondaryStorageEncrypted": false,
    "deprecated": false,
    "correspondingMachineType": "",
    "isTrusted": false,
    "gpus": "",
    "ocp_unsupported": false
  },
  {
    "name": "mx2.8x64",
    "provider": "vpc-gen2",
    "cpu": 8,
    "memory": 64,
    "networkSpeed": "16Gbps",
    "serverType": "virtual",
    "secondaryStorage": "false",
    "secondaryStorageEncrypted": false,
    "deprecated": false,
    "correspondingMachineType": "",
    "isTrusted": false,
    "gpus": "",
    "ocp_unsupported": false
  },
  {
    "name": "bx2.metal.96x384",
    "provider": "vpc-gen2",
    "cpu": 96,
    "memory": 384,
    "networkSpeed": "100Gbps",
    "serverType": "physical",
    "secondaryStorage": "false",
    "secondaryStorageEncrypted": false,
    "deprecated": false,
    "correspondingMachineType": "",
    "isTrusted": false,
    "gpus": "",
    "ocp_unsupported": false
  },
  {
    "name": "bx2d.metal.96x384",
    "provider": "vpc-gen2",
    "cpu": 96,
    "memory": 384,
    "networkSpeed": "100Gbps",
    "serverType": "physical",
    "secondaryStorage": "false",
    "secondaryStorageEncrypted": false,
    "deprecated": false,
    "correspondingMachineType": "",
    "isTrusted": false,
    "gpus": "",
    "ocp_unsupported": false,
    "instanceStorage": [
      8,
      3200,
      "NVMeSSD"
    ]
  },
  {
    "name": "bx3.metal.192x1024",
    "provider": "vpc-gen3",
    "cpu": 192,
    "memory": 1024,
    "networkSpeed": "200Gbps",
    "serverType": "physical",
    "secondaryStorage": "false",
    "secondaryStorageEncrypted": false,
    "deprecated": false,
    "correspondingMachineType": "",
    "isTrusted": false,
    "gpus": "",
    "ocp_unsupported": false
  },
  {
    "name": "bx3.metal.48x256",
    "provider": "vpc-gen3",
    "cpu": 48,
    "memory": 256,
    "networkSpeed": "200Gbps",
    "serverType": "physical",
    "secondaryStorage": "false",
    "secondaryStorageEncrypted": false,
    "deprecated": false,
    "correspondingMachineType": "",
    "isTrusted": false,
    "gpus": "",
    "ocp_unsupported": false
  },
  {
    "name": "bx3.metal.64x256",
    "provider": "vpc-gen3",
    "cpu": 64,
    "memory": 256,
    "networkSpeed": "200Gbps",
    "serverType": "physical",
    "secondaryStorage": "false",
    "secondaryStorageEncrypted": false,
    "deprecated": false,
    "correspondingMachineType": "",
    "isTrusted": false,
    "gpus": "",
    "ocp_unsupported": false
  },
  {
    "name": "bx3d.metal.192x1024",
    "provider": "vpc-gen3",
    "cpu": 192,
    "memory": 1024,
    "networkSpeed": "200Gbps",
    "serverType": "physical",
    "secondaryStorage": "false",
    "secondaryStorageEncrypted": false,
    "deprecated": false,
    "correspondingMachineType": "",
    "isTrusted": false,
    "gpus": "",
    "ocp_unsupported": false,
    "instanceStorage": [
      8,
      7680,
      "NVMeSSD"
    ]
  },
  {
    "name": "bx3d.metal.48x256",
    "provider": "vpc-gen3",
    "cpu": 48,
    "memory": 256,
    "networkSpeed": "200Gbps",
    "serverType": "physical",
    "secondaryStorage": "false",
    "secondaryStorageEncrypted": false,
    "deprecated": false,
    "correspondingMachineType": "",
    "isTrusted": false,
    "gpus": "",
    "ocp_unsupported": false,
    "instanceStorage": [
      4,
      7680,
      "NVMeSSD"
    ]
  },
  {
    "name": "bx3d.metal.64x256",
    "provider": "vpc-gen3",
    "cpu": 64,
    "memory": 256,
    "networkSpeed": "200Gbps",
    "serverType": "physical",
    "secondaryStorage": "false",
    "secondaryStorageEncrypted": false,
    "deprecated": false,
    "correspondingMachineType": "",
    "isTrusted": false,
    "gpus": "",
    "ocp_unsupported": false,
    "instanceStorage": [
      4,
      7680,
      "NVMeSSD"
    ]
  },
  {
    "name": "cx2.metal.96x192",
    "provider": "vpc-gen2",
    "cpu": 96,
    "memory": 192,
    "networkSpeed": "100Gbps",
    "serverType": "physical",
    "secondaryStorage": "false",
    "secondaryStorageEncrypted": false,
    "deprecated": false,
    "correspondingMachineType": "",
    "isTrusted": false,
    "gpus": "",
    "ocp_unsupported": false
  },
  {
    "name": "cx2d.metal.96x192",
    "provider": "vpc-gen2",
    "cpu": 96,
    "memory": 192,
    "networkSpeed": "100Gbps",
    "serverType": "physical",
    "secondaryStorage": "false",
    "secondaryStorageEncrypted": false,
    "deprecated": false,
    "correspondingMachineType": "",
    "isTrusted": false,
    "gpus": "",
    "ocp_unsupported": false,
    "instanceStorage": [
      8,
      3200,
      "NVMeSSD"
    ]
  },
  {
    "name": "cx3.metal.48x128",
    "provider": "vpc-gen3",
    "cpu": 48,
    "memory": 128,
    "networkSpeed": "200Gbps",
    "serverType": "physical",
    "secondaryStorage": "false",
    "secondaryStorageEncrypted": false,
    "deprecated": false,
    "correspondingMachineType": "",
    "isTrusted": false,
    "gpus": "",
    "ocp_unsupported": false
  },
  {
    "name": "cx3.metal.64x128",
    "provider": "vpc-gen3",
    "cpu": 64,
    "memory": 128,
    "networkSpeed": "200Gbps",
    "serverType": "physical",
    "secondaryStorage": "false",
    "secondaryStorageEncrypted": false,
    "deprecated": false,
    "correspondingMachineType": "",
    "isTrusted": false,
    "gpus": "",
    "ocp_unsupported": false
  },
  {
    "name": "cx3d.metal.48x128",
    "provider": "vpc-gen3",
    "cpu": 48,
    "memory": 128,
    "networkSpeed": "200Gbps",
    "serverType": "physical",
    "secondaryStorage": "false",
    "secondaryStorageEncrypted": false,
    "deprecated": false,
    "correspondingMachineType": "",
    "isTrusted": false,
    "gpus": "",
    "ocp_unsupported": false,
    "instanceStorage": [
      4,
      7680,
      "NVMeSSD"
    ]
  },
  {
    "name": "cx3d.metal.64x128",
    "provider": "vpc-gen3",
    "cpu": 64,
    "memory": 128,
    "networkSpeed": "200Gbps",
    "serverType": "physical",
    "secondaryStorage": "false",
    "secondaryStorageEncrypted": false,
    "deprecated": false,
    "correspondingMachineType": "",
    "isTrusted": false,
    "gpus": "",
    "ocp_unsupported": false,
    "instanceStorage": [
      4,
      7680,
      "NVMeSSD"
    ]
  },
  {
    "name": "mx2.metal.96x768",
    "provider": "vpc-gen2",
    "cpu": 96,
    "memory": 768,
    "networkSpeed": "100Gbps",
    "serverType": "physical",
    "secondaryStorage": "false",
    "secondaryStorageEncrypted": false,
    "deprecated": false,
    "correspondingMachineType": "",
    "isTrusted": false,
    "gpus": "",
    "ocp_unsupported": false
  },
  {
    "name": "mx2d.metal.96x768",
    "provider": "vpc-gen2",
    "cpu": 96,
    "memory": 768,
    "networkSpeed": "100Gbps",
    "serverType": "physical",
    "secondaryStorage": "false",
    "secondaryStorageEncrypted": false,
    "deprecated": false,
    "correspondingMachineType": "",
    "isTrusted": false,
    "gpus": "",
    "ocp_unsupported": false,
    "instanceStorage": [
      8,
      3200,
      "NVMeSSD"
    ]
  },
  {
    "name": "mx2de-metal-96x768",
    "provider": "vpc-gen2",
    "cpu": 96,
    "memory": 768,
    "networkSpeed": "100Gbps",
    "serverType": "physical",
    "secondaryStorage": "false",
    "secondaryStorageEncrypted": false,
    "deprecated": false,
    "correspondingMachineType": "",
    "isTrusted": false,
    "gpus": "",
    "ocp_unsupported": false,
    "instanceStorage": [
      16,
      15300,
      "NVMeSSD"
    ]
  },
  {
    "name": "mx3.metal.128x1024",
    "provider": "vpc-gen3",
    "cpu": 128,
    "memory": 1024,
    "networkSpeed": "200Gbps",
    "serverType": "physical",
    "secondaryStorage": "false",
    "secondaryStorageEncrypted": false,
    "deprecated": false,
    "correspondingMachineType": "",
    "isTrusted": false,
    "gpus": "",
    "ocp_unsupported": false
  },
  {
    "name": "mx3.metal.16x128",
    "provider": "vpc-gen3",
    "cpu": 16,
    "memory": 128,
    "networkSpeed": "200Gbps",
    "serverType": "physical",
    "secondaryStorage": "false",
    "secondaryStorageEncrypted": false,
    "deprecated": false,
    "correspondingMachineType": "",
    "isTrusted": false,
    "gpus": "",
    "ocp_unsupported": false
  },
  {
    "name": "mx3.metal.48x512",
    "provider": "vpc-gen3",
    "cpu": 48,
    "memory": 512,
    "networkSpeed": "200Gbps",
    "serverType": "physical",
    "secondaryStorage": "false",
    "secondaryStorageEncrypted": false,
    "deprecated": false,
    "correspondingMachineType": "",
    "isTrusted": false,
    "gpus": "",
    "ocp_unsupported": false
  },
  {
    "name": "mx3.metal.64x512",
    "provider": "vpc-gen3",
    "cpu": 64,
    "memory": 512,
    "networkSpeed": "200Gbps",
    "serverType": "physical",
    "secondaryStorage": "false",
    "secondaryStorageEncrypted": false,
    "deprecated": false,
    "correspondingMachineType": "",
    "isTrusted": false,
    "gpus": "",
    "ocp_unsupported": false
  },
  {
    "name": "mx3.metal.96x1024",
    "provider": "vpc-gen3",
    "cpu": 96,
    "memory": 1024,
    "networkSpeed": "200Gbps",
    "serverType": "physical",
    "secondaryStorage": "false",
    "secondaryStorageEncrypted": false,
    "deprecated": false,
    "correspondingMachineType": "",
    "isTrusted": false,
    "gpus": "",
    "ocp_unsupported": false
  },
  {
    "name": "mx3d.metal.128x1024",
    "provider": "vpc-gen3",
    "cpu": 128,
    "memory": 1024,
    "networkSpeed": "200Gbps",
    "serverType": "physical",
    "secondaryStorage": "false",
    "secondaryStorageEncrypted": false,
    "deprecated": false,
    "correspondingMachineType": "",
    "isTrusted": false,
    "gpus": "",
    "ocp_unsupported": false,
    "instanceStorage": [
      8,
      7680,
      "NVMeSSD"
    ]
  },
  {
    "name": "mx3d.metal.192x2048",
    "provider": "vpc-gen3",
    "cpu": 192,
    "memory": 2048,
    "networkSpeed": "200Gbps",
    "serverType": "physical",
    "secondaryStorage": "false",
    "secondaryStorageEncrypted": false,
    "deprecated": false,
    "correspondingMachineType": "",
    "isTrusted": false,
    "gpus": "",
    "ocp_unsupported": false,
    "instanceStorage": [
      8,
      7680,
      "NVMeSSD"
    ]
  },
  {
    "name": "mx3d.metal.48x512",
    "provider": "vpc-gen3",
    "cpu": 48,
    "memory": 512,
    "networkSpeed": "200Gbps",
    "serverType": "physical",
    "secondaryStorage": "false",
    "secondaryStorageEncrypted": false,
    "deprecated": false,
    "correspondingMachineType": "",
    "isTrusted": false,
    "gpus": "",
    "ocp_unsupported": false,
    "instanceStorage": [
      4,
      7680,
      "NVMeSSD"
    ]
  },
  {
    "name": "mx3d.metal.64x512",
    "provider": "vpc-gen3",
    "cpu": 64,
    "memory": 512,
    "networkSpeed": "200Gbps",
    "serverType": "physical",
    "secondaryStorage": "false",
    "secondaryStorageEncrypted": false,
    "deprecated": false,
    "correspondingMachineType": "",
    "isTrusted": false,
    "gpus": "",
    "ocp_unsupported": false,
    "instanceStorage": [
      4,
      7680,
      "NVMeSSD"
    ]
  },
  {
    "name": "mx3d.metal.96x1024",
    "provider": "vpc-gen3",
    "cpu": 96,
    "memory": 1024,
    "networkSpeed": "200Gbps",
    "serverType": "physical",
    "secondaryStorage": "false",
    "secondaryStorageEncrypted": false,
    "deprecated": false,
    "correspondingMachineType": "",
    "isTrusted": false,
    "gpus": "",
    "ocp_unsupported": false,
    "instanceStorage": [
      8,
      7680,
      "NVMeSSD"
    ]
  },
  {
    "name": "mx3de.metal.48x512",
    "provider": "vpc-gen3",
    "cpu": 48,
    "memory": 512,
    "networkSpeed": "200Gbps",
    "serverType": "physical",
    "secondaryStorage": "false",
    "secondaryStorageEncrypted": false,
    "deprecated": false,
    "correspondingMachineType": "",
    "isTrusted": false,
    "gpus": "",
    "ocp_unsupported": false,
    "instanceStorage": [
      16,
      15300,
      "NVMeSSD"
    ]
  },
  {
    "name": "mx3de.metal.64x512",
    "provider": "vpc-gen3",
    "cpu": 64,
    "memory": 512,
    "networkSpeed": "200Gbps",
    "serverType": "physical",
    "secondaryStorage": "false",
    "secondaryStorageEncrypted": false,
    "deprecated": false,
    "correspondingMachineType": "",
    "isTrusted": false,
    "gpus": "",
    "ocp_unsupported": false,
    "instanceStorage": [
      16,
      15300,
      "NVMeSSD"
    ]
  }
]
